Workbook
Name Slicer_Category: #N/A
Name Slicer_Payment_Method: #N/A
Name Slicer_Region: #N/A

Sheet Raw_Data
A1: Order ID | B1: Order Date | C1: Customer ID | D1: Product | E1: Category | F1: Region | G1: Quantity | H1: Unit Price | I1: Discount % | J1: Payment Method | K1: revenue | L1: cost per unit | M1: profit | N1: profit margin
A2: O0001 | B2: 45985 | C2: C029 | D2: Wireless Earbuds | E2: Electronics | F2: South | G2: 2 | H2: 1999 | I2: 0 | J2: UPI | K2: =G2*H2*(1-I2) -> 3998 | L2: =_xlfn.XLOOKUP(D2,product_cost!A:A,product_cost!B:B) -> 1200 | M2: =K2-(G2*L2) -> 1598 | N2: =M2/K2 -> 0.39969985
A3: O0002 | B3: 46004 | C3: C140 | D3: Bluetooth Speaker | E3: Electronics | F3: North | G3: 2 | H3: 2499 | I3: 0 | J3: Credit Card | K3: =G3*H3*(1-I3) -> 4998 | L3: =_xlfn.XLOOKUP(D3,product_cost!A:A,product_cost!B:B) -> 1600 | M3: =K3-(G3*L3) -> 1798 | N3: =M3/K3 -> 0.3597439
A4: O0003 | B4: 45777 | C4: C130 | D4: Coffee Maker | E4: Home & Kitchen | F4: West | G4: 1 | H4: 3999 | I4: 0 | J4: Credit Card | K4: =G4*H4*(1-I4) -> 3999 | L4: =_xlfn.XLOOKUP(D4,product_cost!A:A,product_cost!B:B) -> 2600 | M4: =K4-(G4*L4) -> 1399 | N4: =M4/K4 -> 0.34983746
A5: O0004 | B5: 45887 | C5: C151 | D5: Phone Case | E5: Accessories | F5: South | G5: 3 | H5: 599 | I5: 0 | J5: Cash on Delivery | K5: =G5*H5*(1-I5) -> 1797 | L5: =_xlfn.XLOOKUP(D5,product_cost!A:A,product_cost!B:B) -> 300 | M5: =K5-(G5*L5) -> 897 | N5: =M5/K5 -> 0.49916528
A6: O0005 | B6: 45832 | C6: C072 | D6: Smart Watch | E6: Electronics | F6: North | G6: 1 | H6: 3499 | I6: 0.1 | J6: UPI | K6: =G6*H6*(1-I6) -> 3149.1 | L6: =_xlfn.XLOOKUP(D6,product_cost!A:A,product_cost!B:B) -> 2300 | M6: =K6-(G6*L6) -> 849.1 | N6: =M6/K6 -> 0.26963259
A7: O0006 | B7: 45852 | C7: C025 | D7: USB-C Cable | E7: Accessories | F7: North | G7: 3 | H7: 399 | I7: 0.1 | J7: Cash on Delivery | K7: =G7*H7*(1-I7) -> 1077.3 | L7: =_xlfn.XLOOKUP(D7,product_cost!A:A,product_cost!B:B) -> 180 | M7: =K7-(G7*L7) -> 537.3 | N7: =M7/K7 -> 0.49874687
A8: O0007 | B8: 45932 | C8: C032 | D8: Running Shoes | E8: Fashion | F8: East | G8: 1 | H8: 2999 | I8: 0 | J8: Net Banking | K8: =G8*H8*(1-I8) -> 2999 | L8: =_xlfn.XLOOKUP(D8,product_cost!A:A,product_cost!B:B) -> 1800 | M8: =K8-(G8*L8) -> 1199 | N8: =M8/K8 -> 0.39979993
A9: O0008 | B9: 45756 | C9: C018 | D9: Wireless Earbuds | E9: Electronics | F9: North | G9: 2 | H9: 1999 | I9: 0.1 | J9: Credit Card | K9: =G9*H9*(1-I9) -> 3598.2 | L9: =_xlfn.XLOOKUP(D9,product_cost!A:A,product_cost!B:B) -> 1200 | M9: =K9-(G9*L9) -> 1198.2 | N9: =M9/K9 -> 0.33299983
A10: O0009 | B10: 45709 | C10: C098 | D10: Phone Case | E10: Accessories | F10: South | G10: 2 | H10: 599 | I10: 0.15 | J10: Debit Card | K10: =G10*H10*(1-I10) -> 1018.3 | L10: =_xlfn.XLOOKUP(D10,product_cost!A:A,product_cost!B:B) -> 300 | M10: =K10-(G10*L10) -> 418.3 | N10: =M10/K10 -> 0.41078268
A11: O0010 | B11: 45839 | C11: C054 | D11: Water Bottle | E11: Home & Kitchen | F11: North | G11: 1 | H11: 799 | I11: 0.15 | J11: Net Banking | K11: =G11*H11*(1-I11) -> 679.15 | L11: =_xlfn.XLOOKUP(D11,product_cost!A:A,product_cost!B:B) -> 400 | M11: =K11-(G11*L11) -> 279.15 | N11: =M11/K11 -> 0.41102849
A12: O0011 | B12: 45983 | C12: C044 | D12: Jeans | E12: Fashion | F12: West | G12: 2 | H12: 1799 | I12: 0 | J12: Debit Card | K12: =G12*H12*(1-I12) -> 3598 | L12: =_xlfn.XLOOKUP(D12,product_cost!A:A,product_cost!B:B) -> 1000 | M12: =K12-(G12*L12) -> 1598 | N12: =M12/K12 -> 0.44413563
A13: O0012 | B13: 45985 | C13: C177 | D13: Jeans | E13: Fashion | F13: North | G13: 1 | H13: 1799 | I13: 0 | J13: Credit Card | K13: =G13*H13*(1-I13) -> 1799 | L13: =_xlfn.XLOOKUP(D13,product_cost!A:A,product_cost!B:B) -> 1000 | M13: =K13-(G13*L13) -> 799 | N13: =M13/K13 -> 0.44413563
... A501: O0500 | B501: 45709 | C501: C087 | D501: Phone Case | E501: Accessories | F501: West | G501: 1 | H501: 599 | I501: 0.2 | J501: Cash on Delivery | K501: =G501*H501*(1-I501) -> 479.2 | L501: =_xlfn.XLOOKUP(D501,product_cost!A:A,product_cost!B:B) -> 300 | M501: =K501-(G501*L501) -> 179.2 | N501: =M501/K501 -> 0.37395659

Sheet product_cost
A1: product | B1: cost per unit
A2: Wireless Earbuds | B2: 1200
A3: Bluetooth Speaker | B3: 1600
A4: Smart Watch | B4: 2300
A5: Laptop Backpack | B5: 750
A6: Phone Case | B6: 300
A7: USB-C Cable | B7: 180
A8: Running Shoes | B8: 1800
A9: Casual T-Shirt | B9: 550
A10: Jeans | B10: 1000
A11: Coffee Maker | B11: 2600
A12: Water Bottle | B12: 400
A13: Desk Lamp | B13: 800

Sheet pivot1
A3: Row Labels | B3: Sum of revenue | C3: Sum of profit
A4: Running Shoes | B4: 256864.35 | C4: 93064.35
A5: Coffee Maker | B5: 289927.5 | C5: 87127.5
A6: Bluetooth Speaker | B6: 267393 | C6: 86593
A7: Smart Watch | B7: 205916.15 | C7: 58716.15
A8: Desk Lamp | B8: 135434.65 | C8: 58634.65
A9: Jeans | B9: 114056.6 | C9: 46056.6
A10: Wireless Earbuds | B10: 128435.75 | C10: 45635.75
A11: Laptop Backpack | B11: 107232.45 | C11: 41982.45
A12: Water Bottle | B12: 56169.7 | C12: 26169.7
A13: Casual T-Shirt | B13: 62837.1 | C13: 25987.1
A14: Phone Case | B14: 30489.1 | C14: 13989.1
A15: USB-C Cable | B15: 25615.8 | C15: 13195.8
A16: Grand Total | B16: 1680372.2 | C16: 597152.15

Sheet pivot2
A3: Row Labels | B3: Average of profit margin
A4: USB-C Cable | B4: 0.51140453
A5: Water Bottle | B5: 0.46343687
A6: Phone Case | B6: 0.45250716
A7: Desk Lamp | B7: 0.42813442
A8: Casual T-Shirt | B8: 0.41092172
A9: Jeans | B9: 0.40235749
A10: Laptop Backpack | B10: 0.39268779
A11: Running Shoes | B11: 0.36365579
A12: Wireless Earbuds | B12: 0.34949341
A13: Bluetooth Speaker | B13: 0.31781586
A14: Coffee Maker | B14: 0.28910871
A15: Smart Watch | B15: 0.28451725
A16: Grand Total | B16: 0.38585066

Sheet pivot3
A3: Row Labels | B3: Sum of revenue | C3: Sum of profit
A4: North | B4: 480992.35 | C4: 168022.35
A5: South | B5: 416117.85 | C5: 146957.85
A6: West | B6: 398502.9 | C6: 145472.9
A7: East | B7: 384759.05 | C7: 136699.05
A8: Grand Total | B8: 1680372.1 | C8: 597152.15

Sheet pivot4
A3: Row Labels | B3: Count of Order ID | C3: Sum of revenue
A4: UPI | B4: 101 | C4: 358663.15
A5: Net Banking | B5: 104 | C5: 338570.95
A6: Cash on Delivery | B6: 86 | C6: 331599.5
A7: Debit Card | B7: 108 | C7: 326539.15
A8: Credit Card | B8: 101 | C8: 324999.4
A9: Grand Total | B9: 500 | C9: 1680372.2

Sheet pivot5
A3: Row Labels | B3: Sum of revenue | C3: Count of Order ID | D3: Sum of profit | E3: Average of profit margin
A4: Electronics | B4: 601744.9 | C4: 132 | D4: 190944.9 | E4: 0.31713377
A5: Home & Kitchen | B5: 481531.85 | C5: 131 | D5: 171931.85 | E5: 0.39487963
A6: Fashion | B6: 433758.05 | C6: 129 | D6: 165108.05 | E6: 0.3900788
A7: Accessories | B7: 163337.35 | C7: 108 | D7: 69167.35 | E7: 0.45383586
A8: Grand Total | B8: 1680372.2 | C8: 500 | D8: 597152.15 | E8: 0.38585066

Sheet pivot6
A3: Row Labels | B3: Sum of revenue | C3: Sum of profit
A4: Jan | B4: 189137.2 | C4: 68407.2
A5: Oct | B5: 190472.3 | C5: 64022.3
A6: May | B6: 164898.75 | C6: 59198.75
A7: Mar | B7: 136163.7 | C7: 48753.7
A8: Aug | B8: 132865.6 | C8: 48745.6
A9: Sep | B9: 133495.25 | C9: 48405.25
A10: Nov | B10: 127957.55 | C10: 46747.55
A11: Apr | B11: 133024.1 | C11: 45554.1
A12: Jun | B12: 124680.4 | C12: 44380.4
A13: Jul | B13: 124477.1 | C13: 43817.1
A14: Feb | B14: 110790.4 | C14: 39870.4
A15: Dec | B15: 112409.8 | C15: 39249.8
A16: Grand Total | B16: 1680372.2 | C16: 597152.15

Sheet pivot7
A3: Row Labels | B3: Sum of revenue | C3: Sum of profit
A4: C166 | B4: 32837.95 | C4: 9837.95
A5: C130 | B5: 29238.35 | C5: 10788.35
A6: C136 | B6: 29061.75 | C6: 9661.75
A7: C179 | B7: 28672.75 | C7: 10522.75
A8: C106 | B8: 27989.15 | C8: 10529.15
A9: C081 | B9: 27421.2 | C9: 9031.2
A10: C100 | B10: 26989.2 | C10: 9469.2
A11: C084 | B11: 24692.5 | C11: 7392.5
A12: C034 | B12: 24593.3 | C12: 7993.3
A13: C174 | B13: 23761.65 | C13: 7961.65
A14: C029 | B14: 23270.75 | C14: 7090.75
A15: C110 | B15: 23100.15 | C15: 8200.15
... A171: Grand Total | B171: 1680372.1 | C171: 597152.15

Sheet Dashboard
A1: E-commerce sales and profit analysis dashboard
A3: total revenue | B3: =GETPIVOTDATA("Sum of revenue",pivot5!$A$3) -> 1680372.2 | C3: total profit | D3: =GETPIVOTDATA("Sum of profit",pivot5!$A$3) -> 597152.15 | E3: total orders | F3: =GETPIVOTDATA("Count of Order ID",pivot5!$A$3) -> 500 | G3: profit margin | H3: =GETPIVOTDATA("Average of profit margin",pivot5!$A$3) -> 0.38585066
M42: Key Bussiness Insights
M44: Running Shoes generated the highest revenue and total profit.
M45: USB-C Cable had the highest average profit margin.
M46: North generated the highest revenue and total profit among regions.
M47: Electronics was the strongest category by revenue and profit.
M48: UPI generated the highest revenue among payment methods.
M49: October had the highest revenue, while January had the highest profit
